{"Searchterm": [], "CL_opinion_download_url": "http://www.ca5.uscourts.gov/opinions/unpub/14/14-40381.0.pdf", "Title": "United States v. Eduardo Soriano-Perez", "Cases_Cited": ["632 F.3d 229", "386 U.S. 738"], "Text_Level_Notes": [], "TF_IDF_Tags": [], "Manual_Tags": [], "Opinion_Date": "2015-03-12 00:00:00", "URL": "http://www.ca5.uscourts.gov/opinions/unpub/14/14-40381.0.pdf", "Year": 2015, "Party1": "United States", "CL_opinion_resource_uri": "http://www.courtlistener.com/api/rest/v3/opinions/2785856/", "Party2": "Eduardo Soriano-Perez", "CL_opinion_date_modified": "2017-04-11T12:44:22.855445Z", "Document_Level_Tags": ["ScrapeSource_CL", "ScrapeDate_06202018"], "HTMLtext": "<pre class=\"inline\">     Case: 14-40381      Document: 00512966344         Page: 1    Date Filed: 03/12/2015\n\n\n\n\n           IN THE UNITED STATES COURT OF APPEALS\n                    FOR THE FIFTH CIRCUIT\n                                                                        United States Court of Appeals\n                                                                                 Fifth Circuit\n\n\n                                    No. 14-40381                               FILED\n                                 Conference Calendar                     March 12, 2015\n                                                                          Lyle W. Cayce\n                                                                               Clerk\nUNITED STATES OF AMERICA,\n\n                                                 Plaintiff-Appellee\n\nv.\n\nEDUARDO SORIANO-PEREZ,\n\n                                                 Defendant-Appellant\n\n\n                   Appeal from the United States District Court\n                        for the Southern District of Texas\n                            USDC No. 5:13-CR-1323-1\n\n\nBefore KING, DENNIS, and SOUTHWICK, Circuit Judges.\nPER CURIAM: *\n       The Federal Public Defender appointed to represent Eduardo Soriano-\nPerez has moved for leave to withdraw and has filed a brief in accordance with\nAnders v. California, </pre><span class=\"citation\" data-id=\"107423\"><a href=\"/opinion/107423/anders-v-california/\"><span class=\"volume\">386</span> <span class=\"reporter\">U.S.</span> <span class=\"page\">738</span></a></span><pre class=\"inline\"> (1967), and United States v. Flores, </pre><span class=\"citation\" data-id=\"183926\"><a href=\"/opinion/183926/united-states-v-flores/\"><span class=\"volume\">632</span> <span class=\"reporter\">F.3d</span>\n<span class=\"page\">229</span></a></span><pre class=\"inline\"> (5th Cir. 2011). Soriano-Perez has not filed a response. We have reviewed\ncounsel\u2019s brief and the relevant portions of the record reflected therein. We\nconcur with counsel\u2019s assessment that the appeal presents no nonfrivolous\n\n\n       * Pursuant to 5TH CIR. R. 47.5, the court has determined that this opinion should not\nbe published and is not precedent except under the limited circumstances set forth in 5TH\nCIR. R. 47.5.4.\n\f    Case: 14-40381    Document: 00512966344    Page: 2   Date Filed: 03/12/2015\n\n\n                                No. 14-40381\n\nissue for appellate review. Accordingly, counsel\u2019s motion for leave to withdraw\nis GRANTED, counsel is excused from further responsibilities herein, and the\nAPPEAL IS DISMISSED. See 5TH CIR. R. 42.2.\n\n\n\n\n                                      2\n\f</pre>", "Case_Text": "     Case: 14-40381      Document: 00512966344         Page: 1    Date Filed: 03/12/2015\n\n\n\n\n           IN THE UNITED STATES COURT OF APPEALS\n                    FOR THE FIFTH CIRCUIT\n                                                                        United States Court of Appeals\n                                                                                 Fifth Circuit\n\n\n                                    No. 14-40381                               FILED\n                                 Conference Calendar                     March 12, 2015\n                                                                          Lyle W. Cayce\n                                                                               Clerk\nUNITED STATES OF AMERICA,\n\n                                                 Plaintiff-Appellee\n\nv.\n\nEDUARDO SORIANO-PEREZ,\n\n                                                 Defendant-Appellant\n\n\n                   Appeal from the United States District Court\n                        for the Southern District of Texas\n                            USDC No. 5:13-CR-1323-1\n\n\nBefore KING, DENNIS, and SOUTHWICK, Circuit Judges.\nPER CURIAM: *\n       The Federal Public Defender appointed to represent Eduardo Soriano-\nPerez has moved for leave to withdraw and has filed a brief in accordance with\nAnders v. California, 386 U.S. 738 (1967), and United States v. Flores, 632 F.3d\n229 (5th Cir. 2011). Soriano-Perez has not filed a response. We have reviewed\ncounsel\u2019s brief and the relevant portions of the record reflected therein. We\nconcur with counsel\u2019s assessment that the appeal presents no nonfrivolous\n\n\n       * Pursuant to 5TH CIR. R. 47.5, the court has determined that this opinion should not\nbe published and is not precedent except under the limited circumstances set forth in 5TH\nCIR. R. 47.5.4.\n\f    Case: 14-40381    Document: 00512966344    Page: 2   Date Filed: 03/12/2015\n\n\n                                No. 14-40381\n\nissue for appellate review. Accordingly, counsel\u2019s motion for leave to withdraw\nis GRANTED, counsel is excused from further responsibilities herein, and the\nAPPEAL IS DISMISSED. See 5TH CIR. R. 42.2.\n\n\n\n\n                                      2\n\f", "Reporter_Citation": "", "CL_opinion_type": "010combined", "ML_Tags_Text": [], "Cited_No": 0, "CL_opinion_sha1": "5d701869c58173f04b1ad9d6c4731929477bb5c6", "Document_Level_Notes": "", "Court": "Court of Appeals for the Fifth Circuit", "Text_Level_Tags": [], "Review_Status": "Yet To Start", "Searchtags": [], "Cases_Cited_Link": ["http://www.courtlistener.com/api/rest/v3/opinions/107423/", "http://www.courtlistener.com/api/rest/v3/opinions/183926/"], "old_Case_Citation": "", "Data_source": "Court Listener", "CL_opinion_date_created": "2015-03-12T18:00:58.027166Z", "CL_opinion_per_curiam": false, "Rule_Tags": "", "ML_Tags": [], "CL_opinion_page_count": 2, "CL_opinion_absolute_url": "/opinion/2785856/united-states-v-eduardo-soriano-perez/", "Duplicate": "No", "HTML_Stored": 1, "ML_Tags_Doc_Level": [], "CL_opinion_extracted_by_ocr": false, "CL_opinion_author_str": "", "PartyType1": "", "CL_opinion_id": "2785856", "Old_Case_No": "", "Case_ID": "United States v. Eduardo Soriano-Perez (March 12,2015)", "CL_opinion_local_path": "pdf/2015/03/12/united_states_v._eduardo_soriano-perez.pdf", "LDA_Model_Tags": [], "CL_opinion_cluster": {"state_cite_two": "", "date_blocked": null, "syllabus": "", "posture": "", "federal_cite_one": "", "case_name_short": "", "date_filed": "2015-03-12", "federal_cite_two": "", "docket": {"court": {"has_opinion_scraper": true, "in_use": true, "url": "http://www.ca5.uscourts.gov/", "start_date": "1891-03-03", "full_name": "Court of Appeals for the Fifth Circuit", "date_modified": "2014-10-31T01:58:10.879000Z", "position": 105.0, "jurisdiction": "F", "has_oral_argument_scraper": true, "resource_uri": "http://www.courtlistener.com/api/rest/v3/courts/ca5/", "citation_string": "5th Cir.", "short_name": "Fifth Circuit", "end_date": null}, "date_blocked": null, "filepath_ia": null, "docket_number": "14-40381", "date_argued": null, "date_reargued": null, "cause": null, "case_name_short": "", "date_filed": null, "filepath_local": null, "date_cert_denied": null, "source": 0, "assigned_to": null, "clusters": ["http://www.courtlistener.com/api/rest/v3/clusters/2785856/"], "jurisdiction_type": null, "audio_files": [], "date_reargument_denied": null, "date_terminated": null, "case_name_full": "", "date_created": "2015-03-12T18:00:58.025103Z", "slug": "united-states-v-eduardo-soriano-perez", "nature_of_suit": null, "date_modified": "2015-03-12T18:00:58.025103Z", "date_cert_granted": null, "jury_demand": null, "blocked": false, "case_name": "United States v. Eduardo Soriano-Perez", "date_last_filing": null, "referred_to": null, "resource_uri": "http://www.courtlistener.com/api/rest/v3/dockets/2641168/", "absolute_url": "/docket/2641168/united-states-v-eduardo-soriano-perez/", "pacer_case_id": null}, "neutral_cite": "", "scotus_early_cite": "", "source": "C", "scdb_id": "", "sub_opinions": ["http://www.courtlistener.com/api/rest/v3/opinions/2785856/"], "lexis_cite": "", "westlaw_cite": "", "panel": [], "specialty_cite_one": "", "scdb_decision_direction": null, "case_name": "United States v. Eduardo Soriano-Perez", "case_name_full": "", "precedential_status": "Unpublished", "date_created": "2015-03-12T18:24:57.331999Z", "slug": "united-states-v-eduardo-soriano-perez", "procedural_history": "", "nature_of_suit": "Direct Criminal", "non_participating_judges": [], "date_modified": "2015-03-12T18:24:57.331999Z", "scdb_votes_majority": null, "state_cite_regional": "", "state_cite_one": "", "blocked": false, "citation_count": 0, "resource_uri": "http://www.courtlistener.com/api/rest/v3/clusters/2785856/", "absolute_url": "/opinion/2785856/united-states-v-eduardo-soriano-perez/", "scdb_votes_minority": null, "citation_id": 2758631, "federal_cite_three": "", "attorneys": "", "state_cite_three": "", "judges": ""}, "PartyType2": "", "CL_opinion_joined_by": [], "CL_opinion_author": null, "Case_No": "14-40381"}