{"old_Case_Citation": "", "HTML_Stored": 1, "CL_opinion_date_modified": "2017-04-15T04:17:12.627627Z", "Review_Status": "Yet To Start", "Text_Level_Notes": [], "Party1": "Dallas Cty Levee Imp Dist No. 6", "Old_Case_No": "", "Case_ID": "Dallas Cty Levee Imp Dist No. 6 v. Rugel (March 04,1931)", "CL_opinion_local_path": "/home/mlissner/columbia/opinions/texas/court_opinions/documents/222498b643f26728.xml", "CL_opinion_author": null, "Reporter_Citation": "36 S.W.2d 188", "CL_opinion_id": "3912034", "CL_opinion_download_url": null, "CL_opinion_resource_uri": "http://www.courtlistener.com/api/rest/v3/opinions/3912034/", "LDA_Model_Tags": [], "Document_Level_Notes": "", "Text_Level_Tags": [], "Searchterm": [], "Case_No": "1224-5590", "CL_opinion_sha1": "2ea5ba8d1f5622a752822b5771d9425c3ec1372e", "Court": "Texas Supreme Court", "Cited_No": 0, "CL_opinion_page_count": null, "CL_opinion_date_created": "2016-07-06T09:40:32.648748Z", "CL_opinion_author_str": "", "PartyType2": "", "CL_opinion_joined_by": [], "ML_Tags": [], "URL": null, "Searchtags": [], "Cases_Cited": [], "Party2": "Rugel", "Year": 1931, "CL_opinion_cluster": {"CL_cluster_scdb_votes_majority": null, "CL_cluster_neutral_cite": "", "CL_cluster_judges": "LEDDY, J.", "CL_cluster_case_name_short": "Rugel", "CL_cluster_scdb_votes_minority": null, "CL_cluster_attorneys": "K. R. Craig, H. B. Sanders, and George A. Titterington, all of Dallas, for plaintiffs in error.\n\nH. B. Thomas, Jr., of Dallas, for defendant in error.", "CL_cluster_date_modified": "2016-07-06T09:40:32.633869Z", "CL_cluster_docket": {"CL_docket_assigned_to": null, "CL_docket_assigned_to_str": "", "CL_docket_resource_uri": "http://www.courtlistener.com/api/rest/v3/dockets/4020026/", "CL_docket_referred_to": null, "CL_docket_clusters": ["http://www.courtlistener.com/api/rest/v3/clusters/4147884/"], "CL_docket_case_name": "Dallas Cty Levee Imp Dist No. 6 v. Rugel", "CL_docket_nature_of_suit": "", "CL_docket_date_reargued": null, "CL_docket_docket_number": "No. 1224-5590.", "CL_docket_date_modified": "2016-07-06T09:40:32.626176Z", "CL_docket_filepath_ia": "", "CL_docket_date_filed": null, "CL_docket_filepath_local": null, "CL_docket_jurisdiction_type": "", "CL_docket_date_cert_denied": null, "CL_docket_date_created": "2016-07-06T09:40:32.626129Z", "CL_docket_date_reargument_denied": null, "CL_docket_blocked": false, "CL_docket_source": 4, "CL_docket_date_blocked": null, "CL_docket_case_name_full": "Dallas County Levee Improvement Dist. No. 6 v. Rugel.", "CL_docket_date_last_filing": null, "CL_docket_slug": "dallas-cty-levee-imp-dist-no-6-v-rugel", "CL_docket_court": {"CL_court_start_date": null, "CL_court_end_date": null, "CL_court_resource_uri": "http://www.courtlistener.com/api/rest/v3/courts/tex/", "CL_court_position": 368.0, "CL_court_url": "http://www.supreme.courts.state.tx.us/", "CL_court_jurisdiction": "S", "CL_court_has_oral_argument_scraper": false, "CL_court_date_modified": "2014-08-08T17:27:09.820000Z", "CL_court_short_name": "Texas Supreme Court", "CL_court_citation_string": "Tex.", "CL_court_in_use": true, "CL_court_has_opinion_scraper": true, "CL_court_full_name": "Texas Supreme Court"}, "CL_docket_audio_files": [], "CL_docket_case_name_short": "Rugel", "CL_docket_date_cert_granted": null, "CL_docket_cause": "", "CL_docket_absolute_url": "/docket/4020026/dallas-cty-levee-imp-dist-no-6-v-rugel/", "CL_docket_pacer_case_id": "", "CL_docket_date_argued": null, "CL_docket_date_terminated": null, "CL_docket_referred_to_str": "", "CL_docket_jury_demand": ""}, "CL_cluster_lexis_cite": "", "CL_cluster_state_cite_two": "", "CL_cluster_slug": "dallas-cty-levee-imp-dist-no-6-v-rugel", "CL_cluster_citation_count": 0, "CL_cluster_precedential_status": "Published", "CL_cluster_state_cite_regional": "36 S.W.2d 188", "CL_cluster_sub_opinions": ["http://www.courtlistener.com/api/rest/v3/opinions/3912034/", "http://www.courtlistener.com/api/rest/v3/opinions/3912033/"], "CL_cluster_absolute_url": "/opinion/4147884/dallas-cty-levee-imp-dist-no-6-v-rugel/", "CL_cluster_scdb_decision_direction": null, "CL_cluster_westlaw_cite": "", "CL_cluster_state_cite_one": "", "CL_cluster_procedural_history": "", "CL_cluster_date_blocked": null, "CL_cluster_specialty_cite_one": "", "CL_cluster_case_name_full": "Dallas County Levee Improvement Dist. No. 6 v. Rugel.", "CL_cluster_federal_cite_two": "", "CL_cluster_nature_of_suit": "", "CL_cluster_scotus_early_cite": "", "CL_cluster_date_filed": "1931-03-04", "CL_cluster_federal_cite_one": "", "CL_cluster_citation_id": null, "CL_cluster_scdb_id": "", "CL_cluster_syllabus": "", "CL_cluster_panel": [], "CL_cluster_federal_cite_three": "", "CL_cluster_posture": "", "CL_cluster_case_name": "Dallas Cty Levee Imp Dist No. 6 v. Rugel", "CL_cluster_non_participating_judges": [], "CL_cluster_source": "Z", "CL_cluster_blocked": false, "CL_cluster_state_cite_three": "", "CL_cluster_resource_uri": "http://www.courtlistener.com/api/rest/v3/clusters/4147884/", "CL_cluster_date_created": "2016-07-06T09:40:32.633823Z"}, "Opinion_Date": "1931-03-04 00:00:00", "ML_Tags_Text": [], "Cases_Cited_Link": [], "CL_opinion_absolute_url": "/opinion/4147884/dallas-cty-levee-imp-dist-no-6-v-rugel/", "CL_opinion_extracted_by_ocr": false, "Rule_Tags": "", "Manual_Tags": [], "Title": "Dallas Cty Levee Imp Dist No. 6 v. Rugel", "PartyType1": "", "Document_Level_Tags": ["ScrapeSource_CL", "ScrapeDate_06202018"], "Case_Text": "", "TF_IDF_Tags": [], "ML_Tags_Doc_Level": [], "Data_source": "Court Listener", "CL_opinion_type": "030concurrence", "Duplicate": "No", "HTMLtext": "<p>Judgments of the district court and Court of Civil Appeals are both reversed, and judgment rendered for the plaintiffs in error, as recommended by the Commission of Appeals. <span class=\"star-pagination\">*Page 231</span> </p>", "CL_opinion_per_curiam": false}